<TestCases>
    <test>
        <testName>BVT-VERIFY-DEPLOYMENT-PROVISION</testName>
        <testScript></testScript>
        <PowershellScript>BVT-VERIFY-DEPLOYMENT-PROVISION.ps1</PowershellScript>
        <files></files>
        <setupType>SingleVM</setupType>
        <Platform>Azure,HyperV</Platform>
        <Category>BVT</Category>
        <Area>BVT</Area>
        <Tags>bvt,boot</Tags>
        <TestID>AzureBVT_001</TestID>
    </test>
    <test>
        <testName>BVT-IS-ROOT-PASSWORD-DELETED</testName>
        <testScript>BVT-IS-ROOT-PASSWORD-DELETED.py</testScript>
        <PowershellScript>BVT-IS-ROOT-PASSWORD-DELETED.ps1</PowershellScript>
        <files>.\Testscripts\Linux\BVT-IS-ROOT-PASSWORD-DELETED.py,.\Testscripts\Linux\azuremodules.py</files>
        <setupType>BVTDeployment</setupType>
        <Platform>Azure,HyperV</Platform>
        <Category>BVT</Category>
        <Area>BVT</Area>
        <Tags>bvt</Tags>
        <TestID>AzureBVT_003</TestID>
    </test>
    <test>
        <testName>BVT-ROOT-DEVICE-TIMEOUT-CHECK</testName>
        <testScript>BVT-ROOT-DEVICE-TIMEOUT-CHECK.py</testScript>
        <PowershellScript>BVT-ROOT-DEVICE-TIMEOUT-CHECK.ps1</PowershellScript>
        <files>.\Testscripts\Linux\azuremodules.py,.\Testscripts\Linux\BVT-ROOT-DEVICE-TIMEOUT-CHECK.py</files>
        <setupType>BVTDeployment</setupType>
        <Platform>Azure,HyperV</Platform>
        <Category>BVT</Category>
        <Area>BVT</Area>
        <Tags>bvt</Tags>
        <TestID>AzureBVT_006</TestID>
    </test>
    <test>
        <testName>BVT-HVMODULES-CHECK</testName>
        <testScript>BVT-HVMODULES-CHECK.py</testScript>
        <PowershellScript>BVT-HVMODULES-CHECK.ps1</PowershellScript>
        <files>.\Testscripts\Linux\azuremodules.py,.\Testscripts\Linux\BVT-HVMODULES-CHECK.py</files>
        <setupType>BVTDeployment</setupType>
        <Platform>Azure,HyperV</Platform>
        <Category>BVT</Category>
        <Area>BVT</Area>
        <Tags>bvt</Tags>
        <TestID>AzureBVT_007</TestID>
    </test>
    <test>
        <testName>BVT-SWAP-CHECK</testName>
        <testScript>BVT-SWAP-CHECK.py</testScript>
        <PowershellScript>BVT-SWAP-CHECK.ps1</PowershellScript>
        <files>.\Testscripts\Linux\azuremodules.py,.\Testscripts\Linux\BVT-SWAP-CHECK.py</files>
        <setupType>BVTDeployment</setupType>
        <Platform>Azure,HyperV</Platform>
        <Category>BVT</Category>
        <Area>BVT</Area>
        <Tags>bvt</Tags>
        <TestID>AzureBVT_009</TestID>
    </test>
    <test>
        <testName>BVT-MTAB-ENTRY-CHECK</testName>
        <testScript>BVT-MTAB-ENTRY-CHECK.py</testScript>
        <PowershellScript>BVT-MTAB-ENTRY-CHECK.ps1</PowershellScript>
        <files>.\Testscripts\Linux\azuremodules.py,.\Testscripts\Linux\BVT-MTAB-ENTRY-CHECK.py</files>
        <setupType>BVTDeployment</setupType>
        <Platform>Azure</Platform>
        <Category>BVT</Category>
        <Area>BVT</Area>
        <Tags>bvt</Tags>
        <TestID>AzureBVT_010</TestID>
    </test>
    <test>
        <testName>BVT-LAST-CONSOLE-CHECK</testName>
        <testScript>BVT-LAST-CONSOLE-CHECK.py</testScript>
        <PowershellScript>BVT-LAST-CONSOLE-CHECK.ps1</PowershellScript>
        <files>.\Testscripts\Linux\azuremodules.py,.\Testscripts\Linux\BVT-LAST-CONSOLE-CHECK.py</files>
        <setupType>BVTDeployment</setupType>
        <Platform>Azure,HyperV</Platform>
        <Category>BVT</Category>
        <Area>BVT</Area>
        <Tags>bvt</Tags>
        <TestID>AzureBVT_011</TestID>        
    </test>
    <test>
        <testName>BVT-VERIFY-BOOT-ERROR-WARNINGS</testName>
        <testScript>BVT-VERIFY-BOOT-ERROR-WARNINGS.py</testScript>
        <PowershellScript>BVT-VERIFY-BOOT-ERROR-WARNINGS.ps1</PowershellScript>
        <files>.\Testscripts\Linux\azuremodules.py,.\Testscripts\Linux\BVT-VERIFY-BOOT-ERROR-WARNINGS.py,.\XML\Other\ignorable-boot-errors.xml</files>
        <setupType>BVTDeployment</setupType>
        <Platform>Azure,HyperV</Platform>
        <Category>BVT</Category>
        <Area>BVT</Area>
        <Tags>bvt</Tags>
        <TestID>AzureBVT_014</TestID>
    </test>
    <test>
        <testName>BVT-VERIFY-SHUTDOWN</testName>
        <testScript></testScript>
        <PowershellScript>BVT-VERIFY-SHUTDOWN.ps1</PowershellScript>
        <files></files>
        <setupType>BVTDeployment</setupType>
        <Platform>Azure</Platform>
        <Category>BVT</Category>
        <Area>BVT</Area>
        <Tags>bvt</Tags>
        <TestID>AzureBVT_015</TestID>
    </test>
    <test>
        <testName>BVT-VERIFY-UUID-FSTAB</testName>
        <testScript>BVT-VERIFY-UUID-FSTAB.py</testScript>
        <PowershellScript>BVT-VERIFY-UUID-FSTAB.ps1</PowershellScript>
        <files>.\Testscripts\Linux\azuremodules.py,.\Testscripts\Linux\BVT-VERIFY-UUID-FSTAB.py</files>
        <setupType>BVTDeployment</setupType>
        <Platform>Azure,HyperV</Platform>
        <Category>BVT</Category>
        <Area>BVT</Area>
        <Tags>bvt</Tags>
        <TestID>AzureBVT_018</TestID>
    </test>
    <test>
        <testName>BVT-VERIFY-SSHD-CONFIG</testName>
        <testScript>BVT-VERIFY-SSHD-CONFIG.py</testScript>
        <PowershellScript>BVT-VERIFY-SSHD-CONFIG.ps1</PowershellScript>
        <files>.\Testscripts\Linux\azuremodules.py,.\Testscripts\Linux\BVT-VERIFY-SSHD-CONFIG.py</files>
        <setupType>BVTDeployment</setupType>
        <Platform>Azure,HyperV</Platform>
        <Category>BVT</Category>
        <Area>BVT</Area>
        <Tags>bvt</Tags>
        <TestID>AzureBVT_020</TestID>
    </test>
    <test>
        <testName>BVT-VERIFY-VHD-PREREQUISITES</testName>
        <testScript>BVT-VERIFY-VHD-PREREQUISITES.py</testScript>
        <PowershellScript>BVT-VERIFY-VHD-PREREQUISITES.ps1</PowershellScript>
        <files>.\Testscripts\Linux\azuremodules.py,.\Testscripts\Linux\BVT-VERIFY-VHD-PREREQUISITES.py</files>
        <setupType>BVTDeployment</setupType>
        <Platform>Azure,HyperV</Platform>
        <Category>BVT</Category>
        <Area>BVT</Area>
        <Tags>bvt</Tags>
        <TestID>AzureBVT_021</TestID>
    </test>
    <test>
        <testName>BVT-VERIFY-NO-ERROR-IN-LOGS</testName>
        <testScript>BVT-VERIFY-NO-ERROR-IN-LOGS.py</testScript>
        <PowershellScript>BVT-VERIFY-NO-ERROR-IN-LOGS.ps1</PowershellScript>
        <files>.\Testscripts\Linux\azuremodules.py,.\Testscripts\Linux\BVT-VERIFY-NO-ERROR-IN-LOGS.py,.\XML\Other\ignorable-walalog-errors.xml</files>
        <setupType>BVTDeployment</setupType>
        <Platform>Azure,HyperV</Platform>
        <Category>BVT</Category>
        <Area>BVT</Area>
        <Tags>bvt</Tags>
        <TestID>AzureBVT_023</TestID>
    </test>
    <test>
        <testName>BVT-VERIFY-VERBOSE-ENABLED-LOGS</testName>
        <testScript>BVT-VERIFY-VERBOSE-ENABLED-LOGS.py</testScript>
        <PowershellScript>BVT-VERIFY-VERBOSE-ENABLED-LOGS.ps1</PowershellScript>
        <files>.\Testscripts\Linux\azuremodules.py,.\Testscripts\Linux\BVT-VERIFY-VERBOSE-ENABLED-LOGS.py</files>
        <setupType>BVTDeployment</setupType>
        <Platform>Azure,HyperV</Platform>
        <Category>BVT</Category>
        <Area>BVT</Area>
        <Tags>bvt</Tags>
        <TestID>AzureBVT_024</TestID>
    </test>
    <test>
        <testName>BVT-VERIFY-BASH-HISTORY</testName>
        <testScript>BVT-VERIFY-BASH-HISTORY.py</testScript>
        <PowershellScript>BVT-VERIFY-BASH-HISTORY.ps1</PowershellScript>
        <files>.\Testscripts\Linux\azuremodules.py,.\Testscripts\Linux\BVT-VERIFY-BASH-HISTORY.py</files>
        <setupType>BVTDeployment</setupType>
        <Platform>Azure,HyperV</Platform>
        <Category>BVT</Category>
        <Area>BVT</Area>
        <Tags>bvt</Tags>
        <TestID>AzureBVT_025</TestID>
    </test>
    <test>
        <testName>BVT-PASSWD-POLICY-TEST</testName>
        <testScript>BVT-PASSWD-POLICY-TEST.py</testScript>
        <PowershellScript>BVT-PASSWD-POLICY-TEST.ps1</PowershellScript>
        <files>.\Testscripts\Linux\BVT-PASSWD-POLICY-TEST.py,.\Testscripts\Linux\azuremodules.py</files>
        <setupType>BVTDeployment</setupType>
        <TestType>
        </TestType>
        <TestFeature>
        </TestFeature>
        <Platform>Azure</Platform>
        <Category>BVT</Category>
        <Area>BVT</Area>
        <Tags>bvt</Tags>
        <TestID>AzureBVT_026</TestID>
    </test>
    <test>
        <testName>BVT-VERIFY-KVP-DAEMON-STATUS</testName>
        <testScript></testScript>
        <PowershellScript>BVT-VERIFY-KVP-DAEMON-STATUS.ps1</PowershellScript>
        <files></files>
        <setupType>BVTDeployment</setupType>
        <Platform>Azure,HyperV</Platform>
        <Category>BVT</Category>
        <Area>BVT</Area>
        <Tags>bvt</Tags>
        <TestID>AzureBVT_029</TestID>
    </test>
</TestCases>