<TestCases>
    <test>
        <testName>VERIFY-DPDK-BUILD-AND-TESTPMD-TEST</testName>
        <testScript>VERIFY-DPDK-BUILD-AND-TESTPMD-TEST.ps1</testScript>
        <setupType>DPDK</setupType>
        <AdditionalHWConfig>
            <Networking>SRIOV</Networking>
        </AdditionalHWConfig>        
        <SubtestValues>This-tag-will-be-removed</SubtestValues>
        <files>.\Testscripts\Linux\azuremodules.sh</files>
        <TestParameters>
            <param>dpdkSrcLink="https://eosgcloudstorage.blob.core.windows.net/testpackages/dpdk/dpdk-18.05.tar.xz"</param>
            <param>testDuration=120</param>
            <param>modes="rxonly io"</param>
        </TestParameters>
        <Platform>Azure</Platform>
        <Category>Functional</Category>
        <Area>DPDK</Area>
        <Tags>dpdk,network,hv_netvsc,sriov</Tags>
    </test>	
</TestCases>