{
    "testcases": [
        {
            "name": "randread",
            "filename": "Random_Read_Size_1G",
            "testcase_name": "random_read_with_1gb",
            "ioengine": "libaio",
            "iodepth": 1,
            "mode": "randread",
            "block_size": "4k",
            "direct": 0,
            "size_mb": 1024,
            "numjob": 4,
            "time": 240,
            "group_reporting": true
        },
        {
            "name": "randread",
            "filename": "Random_Read_Size_4G",
            "testcase_name": "random_read_with_4gb",
            "ioengine": "libaio",
            "iodepth": 1,
            "mode": "randread",
            "block_size": "4k",
            "direct": 0,
            "size_mb": 4096,
            "numjob": 4,
            "time": 240,
            "group_reporting": true
        },
        {
            "name": "read",
            "filename": "Read_Size_1G",
            "testcase_name": "read_with_1gb",
            "ioengine": "libaio",
            "iodepth": 1,
            "mode": "read",
            "block_size": "4k",
            "direct": 0,
            "size_mb": 1024,
            "numjob": 4,
            "time": 240,
            "group_reporting": true
        },
        {
            "name": "read",
            "filename": "Read_Size_4G",
            "testcase_name": "read_with_4gb",
            "ioengine": "libaio",
            "iodepth": 1,
            "mode": "read",
            "block_size": "4k",
            "direct": 0,
            "size_mb": 4096,
            "numjob": 4,
            "time": 240,
            "group_reporting": true
        },
        {
            "name": "randwrite",
            "filename": "Random_Write_Size_1G",
            "testcase_name": "random_write_with_1gb",
            "ioengine": "libaio",
            "iodepth": 1,
            "mode": "randwrite",
            "block_size": "4k",
            "direct": 0,
            "size_mb": 1024,
            "numjob": 4,
            "time": 240,
            "group_reporting": true
        },
        {
            "name": "randwrite",
            "filename": "Random_Write_Size_4G",
            "testcase_name": "random_write_with_4gb",
            "ioengine": "libaio",
            "iodepth": 1,
            "mode": "randwrite",
            "block_size": "4k",
            "direct": 0,
            "size_mb": 4096,
            "numjob": 4,
            "time": 240,
            "group_reporting": true
        },
        {
            "name": "write",
            "filename": "Write_Size_1G",
            "testcase_name": "write_with_1gb",
            "ioengine": "libaio",
            "iodepth": 1,
            "mode": "write",
            "block_size": "4k",
            "direct": 0,
            "size_mb": 1024,
            "numjob": 4,
            "time": 240,
            "group_reporting": true
        },
        {
            "name": "write",
            "filename": "Write_Size_4G",
            "testcase_name": "write_with_4gb",
            "ioengine": "libaio",
            "iodepth": 1,
            "mode": "write",
            "block_size": "4k",
            "direct": 0,
            "size_mb": 4096,
            "numjob": 4,
            "time": 240,
            "group_reporting": true
        }
    ]
}